pheval_gado/__init__.py
pheval_gado/cli.py
pheval_gado/constants.py
pheval_gado/post_process/__init__.py
pheval_gado/post_process/post_process.py
pheval_gado/post_process/post_process_results_format.py
pheval_gado/prepare/__init__.py
pheval_gado/prepare/create_input_data.py
pheval_gado/prepare/prepare.py
pheval_gado/prepare/prepare_commands.py
pheval_gado/run/__init__.py
pheval_gado/run/run.py
pheval_gado/runner.py
pheval_gado/tool_specific_configuration_parser.py
pheval_gado-0.3.0.dist-info/METADATA
pheval_gado-0.3.0.dist-info/WHEEL
pheval_gado-0.3.0.dist-info/entry_points.txt
pheval_gado-0.3.0.dist-info/RECORD
