Metadata-Version: 2.4
Name: pheval-gado
Version: 0.3.0
Summary: 
Author: Yasemin Bridges
Author-email: y.bridges@qmul.ac.uk
Requires-Python: >=3.10,<4.0
Classifier: Programming Language :: Python :: 3
Classifier: Programming Language :: Python :: 3.10
Classifier: Programming Language :: Python :: 3.11
Classifier: Programming Language :: Python :: 3.12
Classifier: Programming Language :: Python :: 3.13
Classifier: Programming Language :: Python :: 3.14
Requires-Dist: pheval (>=0.6.6,<0.7.0)
